sharp_frames/__init__.py
sharp_frames/selection_methods.py
sharp_frames/selection_preview.py
sharp_frames/sharp_frames.py
sharp_frames/sharp_frames_processor.py
sharp_frames/textual_interface.py
sharp_frames/video_utils.py
sharp_frames/models/__init__.py
sharp_frames/models/frame_data.py
sharp_frames/processing/__init__.py
sharp_frames/processing/frame_extractor.py
sharp_frames/processing/frame_saver.py
sharp_frames/processing/frame_selector.py
sharp_frames/processing/minimal_progress.py
sharp_frames/processing/sharpness_analyzer.py
sharp_frames/processing/tui_processor.py
sharp_frames/ui/__init__.py
sharp_frames/ui/app.py
sharp_frames/ui/constants.py
sharp_frames/ui/styles.py
sharp_frames/ui/components/__init__.py
sharp_frames/ui/components/step_handlers.py
sharp_frames/ui/components/validators.py
sharp_frames/ui/screens/__init__.py
sharp_frames/ui/screens/configuration.py
sharp_frames/ui/screens/configuration_original.py
sharp_frames/ui/screens/processing.py
sharp_frames/ui/screens/selection.py
sharp_frames/ui/utils/__init__.py
sharp_frames/ui/utils/context_managers.py
sharp_frames/ui/utils/error_analysis.py
sharp_frames/ui/utils/path_sanitizer.py
sharp_frames-0.3.1.dist-info/licenses/LICENSE
sharp_frames-0.3.1.dist-info/METADATA
sharp_frames-0.3.1.dist-info/WHEEL
sharp_frames-0.3.1.dist-info/entry_points.txt
sharp_frames-0.3.1.dist-info/top_level.txt
sharp_frames-0.3.1.dist-info/RECORD
