Metadata-Version: 2.4
Name: sharp-frames
Version: 0.3.1
Summary: Extract, score, and select the best frames from a video or image directory
Author-email: "Reflct.app" <info@reflct.app>
License: MIT
Project-URL: Homepage, https://github.com/reflct/sharp-frames-python
Project-URL: Documentation, https://github.com/reflct/sharp-frames-python#readme
Project-URL: Changelog, https://github.com/reflct/sharp-frames-python/blob/main/CHANGELOG.md
Keywords: video,frames,sharpness,image-processing
Classifier: Programming Language :: Python :: 3
Classifier: Programming Language :: Python :: 3.7
Classifier: Programming Language :: Python :: 3.8
Classifier: Programming Language :: Python :: 3.9
Classifier: Programming Language :: Python :: 3.10
Classifier: Programming Language :: Python :: 3.11
Classifier: License :: OSI Approved :: MIT License
Classifier: Operating System :: OS Independent
Classifier: Topic :: Multimedia :: Video
Classifier: Topic :: Multimedia :: Graphics
Classifier: Intended Audience :: End Users/Desktop
Requires-Python: >=3.7
License-File: LICENSE
Requires-Dist: opencv-python>=4.5.0
Requires-Dist: numpy>=1.19.0
Requires-Dist: tqdm>=4.64.0
Requires-Dist: textual>=0.41.0
Dynamic: license-file
